lesma/__init__.py
lesma/main.py
lesma/app/__init__.py
lesma/app/lesma.py
lesma/app/static/css/lesma.css
lesma/app/static/img/favicon-128.png
lesma/app/static/img/favicon-16.png
lesma/app/static/img/favicon-256.png
lesma/app/static/img/favicon-32.png
lesma/app/static/img/favicon-512.png
lesma/app/static/img/favicon-64.png
lesma/app/static/img/favicon.ico
lesma/app/static/js/lesma.js
lesma/app/templates/404.html
lesma/app/templates/help.html
lesma/app/templates/help.txt
lesma/app/templates/index.html
lesma/app/templates/layout.html
lesma/app/templates/lesma.html
lesma-0.5.4.dist-info/LICENSE
lesma-0.5.4.dist-info/METADATA
lesma-0.5.4.dist-info/WHEEL
lesma-0.5.4.dist-info/entry_points.txt
lesma-0.5.4.dist-info/top_level.txt
lesma-0.5.4.dist-info/RECORD
