Metadata-Version: 2.1
Name: lesma
Version: 0.5.4
Summary: Simple paste app, friendly with browser and command line, with files as storage backend.
Home-page: https://lesma.eu
Author: Óscar García Amor
Author-email: ogarcia@connectical.com
License: GPLv3
Project-URL: Bug Reports, https://github.com/ogarcia/lesma/issues
Project-URL: Source, https://github.com/ogarcia/lesma
Keywords: lesma paste pastebin sprunge pastein hastebin friendly commandline
Classifier: Development Status :: 4 - Beta
Classifier: Environment :: Web Environment
Classifier: Framework :: Flask
Classifier: Intended Audience :: Developers
Classifier: Intended Audience :: System Administrators
Classifier: License :: OSI Approved :: GNU General Public License v3 (GPLv3)
Classifier: Natural Language :: English
Classifier: Operating System :: OS Independent
Classifier: Programming Language :: Python :: 3
Classifier: Topic :: Utilities
License-File: LICENSE
Requires-Dist: flask
Requires-Dist: gevent
Requires-Dist: pygments
